{
  "version": 1,
  "license": "CC-BY-SA-3.0",
  "copyright": "Taken from https://github.com/tgstation/TerraGov-Marine-Corps/commit/dde92f4fff17ec5171210d41d9b73daba36f5833",
  "size": {
    "x": 32,
    "y": 32
  },
  "states": [
    {
      "name": "base"
    },
    {
      "name": "weed0"
    },
    {
      "name": "weed1"
    },
    {
      "name": "weed2"
    },
    {
      "name": "weed3"
    },
    {
      "name": "weed4"
    },
    {
      "name": "weed5"
    },
    {
      "name": "weed6"
    },
    {
      "name": "weed7"
    },
    {
      "name": "weed8"
    },
    {
      "name": "weed9"
    },
    {
      "name": "weed10"
    },
    {
      "name": "weed11"
    },
    {
      "name": "weed12"
    },
    {
      "name": "weed13"
    },
    {
      "name": "weed14"
    },
    {
      "name": "weed15"
    },
    {
      "name": "weed_dir14"
    },
    {
      "name": "weed_dir10"
    },
    {
      "name": "weed_dir11"
    },
    {
      "name": "weed_dir9"
    },
    {
      "name": "weed_dir13"
    },
    {
      "name": "weed_dir5"
    },
    {
      "name": "weed_dir7"
    },
    {
      "name": "weed_dir6"
    },
    {
      "name": "weed_dir2"
    },
    {
      "name": "weed_dir8"
    },
    {
      "name": "weed_dir1"
    },
    {
      "name": "weed_dir4"
    },
    {
      "name": "weed_dir12"
    },
    {
      "name": "weed_dir3"
    },
    {
      "name": "weedwall0"
    },
    {
      "name": "weedwall1"
    },
    {
      "name": "weedwall2"
    },
    {
      "name": "weedwall3"
    },
    {
      "name": "weedwall4"
    },
    {
      "name": "weedwall5"
    },
    {
      "name": "weedwall6"
    },
    {
      "name": "weedwall7"
    },
    {
      "name": "weedwall8"
    },
    {
      "name": "weedwall9"
    },
    {
      "name": "weedwall10"
    },
    {
      "name": "weedwall11"
    },
    {
      "name": "weedwall12"
    },
    {
      "name": "weedwall13"
    },
    {
      "name": "weedwall14"
    },
    {
      "name": "weedwall15"
    },
    {
      "name": "weedwall"
    },
    {
      "name": "weednode",
      "delays": [
        [
          1.2,
          0.1,
          0.1,
          0.1,
          0.1,
          0.1,
          0.3
        ]
      ]
    },
    {
      "name": "weedframe0"
    },
    {
      "name": "weedframe1"
    },
    {
      "name": "weedframe2"
    },
    {
      "name": "weedframe3"
    },
    {
      "name": "weedframe4"
    },
    {
      "name": "weedframe8"
    },
    {
      "name": "weedframe12"
    },
    {
      "name": "weed_dir0"
    },
    {
      "name": "weed_dir15"
    }
  ]
}
